{"namedChunkGroups":{"polyfill":{"name":"polyfill","assets":[{"name":"webpack-runtime-b6c77ce23b9bf2c8d606.js","size":4310},{"name":"polyfill-eea0097729530b303889.js","size":85274}],"filteredAssets":0,"assetsSize":89584,"filteredAuxiliaryAssets":2,"auxiliaryAssetsSize":225291},"app":{"name":"app","assets":[{"name":"webpack-runtime-b6c77ce23b9bf2c8d606.js","size":4310},{"name":"styles.a1c7c66b35e6b878c3f5.css","size":14192},{"name":"framework-794e842e1cfe3829ffdd.js","size":128852},{"name":"app-8590110121ee67c1a3b6.js","size":49786}],"filteredAssets":0,"assetsSize":197140,"filteredAuxiliaryAssets":3,"auxiliaryAssetsSize":546284},"component---src-pages-404-js":{"name":"component---src-pages-404-js","assets":[{"name":"component---src-pages-404-js-06fd7255a68f1e080def.js","size":793}],"filteredAssets":0,"assetsSize":793,"filteredAuxiliaryAssets":1,"auxiliaryAssetsSize":1865},"component---src-pages-index-js":{"name":"component---src-pages-index-js","assets":[{"name":"styles.a1c7c66b35e6b878c3f5.css","size":14192},{"name":"component---src-pages-index-js-7ae71aebb919ea8bef6f.js","size":5672}],"filteredAssets":0,"assetsSize":19864,"filteredAuxiliaryAssets":1,"auxiliaryAssetsSize":25382}},"assetsByChunkName":{"polyfill":["webpack-runtime-b6c77ce23b9bf2c8d606.js","polyfill-eea0097729530b303889.js"],"app":["webpack-runtime-b6c77ce23b9bf2c8d606.js","styles.a1c7c66b35e6b878c3f5.css","framework-794e842e1cfe3829ffdd.js","app-8590110121ee67c1a3b6.js"],"component---src-pages-404-js":["component---src-pages-404-js-06fd7255a68f1e080def.js"],"component---src-pages-index-js":["styles.a1c7c66b35e6b878c3f5.css","component---src-pages-index-js-7ae71aebb919ea8bef6f.js"]},"childAssetsByChunkName":{}}